INSTALL.rst
LICENSE
MANIFEST.in
README.rst
setup.cfg
setup.py
src/jarbas_tasks/__init__.py
src/jarbas_tasks/__main__.py
src/jarbas_tasks/main.py
src/jarbas_tasks/tasks.py
src/jarbas_tasks/util.py
src/jarbas_tasks.egg-info/PKG-INFO
src/jarbas_tasks.egg-info/SOURCES.txt
src/jarbas_tasks.egg-info/dependency_links.txt
src/jarbas_tasks.egg-info/entry_points.txt
src/jarbas_tasks.egg-info/not-zip-safe
src/jarbas_tasks.egg-info/requires.txt
src/jarbas_tasks.egg-info/top_level.txt
src/jarbas_tasks/data/bashrc
src/jarbas_tasks/data/docker-bashrc