Metadata-Version: 1.1
Name: jarbas-tasks
Version: 0.1.0
Summary: Reuse invoke tasks in your Jarbas projects and containers.
Home-page: https://github.com/fabiommendes/jarbas-tasks
Author: Fábio Macêdo Mendes
Author-email: fabiomacedomendes@gmail.com
License: GNU General Public License (GPL)
Keywords: automation,devops,tools
Platform: UNKNOWN
Classifier: Development Status :: 4 - Beta
Classifier: Intended Audience :: Developers
Classifier: Operating System :: POSIX
Classifier: Programming Language :: Python
Classifier: Programming Language :: Python :: 3
Classifier: Programming Language :: Python :: 3.4
Classifier: Programming Language :: Python :: 3.5
Classifier: Programming Language :: Python :: 3.6
Classifier: Topic :: Software Development :: Libraries
